fastapi_g/__init__.py
fastapi_g/main.py
fastapi_g-0.1.2.dist-info/METADATA
fastapi_g-0.1.2.dist-info/WHEEL
fastapi_g-0.1.2.dist-info/entry_points.txt
fastapi_g-0.1.2.dist-info/top_level.txt
fastapi_g-0.1.2.dist-info/RECORD
