Metadata-Version: 2.1
Name: fastapi-g
Version: 0.1.2
Author: Ashary Gartanto
Author-email: ashary.gartanto@gmail.com
Requires-Dist: pydantic
Requires-Dist: fastapi
Requires-Dist: tqdm
